Workbook

Sheet Task Brief
A1: T38 Employee survey theme coder
A2: Mini project | 30 marks | Build something with free LLM tools
A4: Task ID | B4: T38
A5: Task | B5: Employee survey theme coder
A6: Theme | B6: AI text analytics
A7: Suggested free tools | B7: Free tiers of ChatGPT, Gemini, Claude or Microsoft Copilot; Excel / Google Sheets to score results
A8: What students do | B8: 1. Ask an LLM to propose themes, then refine them into a codebook. 2. Code all open comments using the codebook. 3. Check 50 codings by hand against the gold labels. 4. Link themes to low Likert scores and write an HR action plan.
A9: Deliverables | B9: Codebook; coded responses; accuracy check; action plan; AI-use log
A10: Dataset in this file | B10: 300 engagement survey responses with open comments - 'Responses' sheet: 300 rows x 10 columns - 'Gold Labels (evaluation)' sheet: 300 rows x 3 columns
A11: About the data | B11: All data is synthetic and created for teaching; companies, people and figures are fictional. Treat it as if it were real business data. If a 'Gold Labels (evaluation)' sheet is present, do NOT give it to the AI tool - use it only at the end to measure your accuracy.
A12: Team size | B12: Individual (or pairs if your faculty allows)
A13: Responsible AI rules | B13: Use only free tools; never paste real personal or confidential data into public AI tools; verify every number the AI gives you; disclose AI-generated content.
A14: Submission | B14: 1) Build link / file / screen recording 2) This workbook with your outputs added as new sheets 3) Completed 'AI Use Log' sheet (minimum 15 entries) 4) 3-5 page report with recommendation and reflection
A16: Evaluation rubric (30 marks)
A17: Criterion | B17: What is assessed | C17: Marks | D17: Excellent | E17: Good | F17: Fair | G17: Poor
A18: 1. Working build | B18: Tool / bot / app / automation works end to end on the provided data; link, file or screen recording submitted | C18: 8 | D18: Runs fully (7-8) | E18: Minor gaps (5-6) | F18: Partly working (3-4) | G18: Not working (0-2)
A19: 2. Correctness and verification | B19: Outputs checked against the data or gold labels; accuracy measured; errors found and fixed | C19: 7 | D19: Systematic checks with numbers (6-7) | E19: Some checks (4-5) | F19: Few checks (2-3) | G19: None (0-1)
A20: 3. Prompting and iteration | B20: Clear, structured prompts; at least 3 documented improvement rounds with reasons | C20: 5 | D20: Strong iteration (5) | E20: Some iteration (3-4) | F20: Mostly one-shot (2) | G20: No log (0-1)
A21: 4. Business insight and recommendation | B21: Specific, data-backed recommendation for the stated manager or customer | C21: 6 | D21: Actionable and quantified (6) | E21: Sound but generic (4-5) | F21: Descriptive only (2-3) | G21: Missing (0-1)
A22: 5. Documentation and reflection | B22: Complete AI-use log, limitations, responsible-AI notes and personal reflection | C22: 4 | D22: Complete and honest (4) | E22: Mostly complete (3) | F22: Thin (2) | G22: Missing (0-1)
A23: Total | C23: =SUM(C18:C22) -> 30

Sheet Responses
A1: response_id | B1: department | C1: tenure_band | D1: q1_clear_goals_1to5 | E1: q2_manager_support_1to5 | F1: q3_fair_pay_1to5 | G1: q4_growth_1to5 | H1: q5_worklife_balance_1to5 | I1: enps_0to10 | J1: open_comment
A2: R0001 | B2: Technology | C2: 3-5 yrs | D2: 4 | E2: 4 | F2: 5 | G2: 3 | H2: 5 | I2: 8 | J2: My manager gives regular, useful feedback.
A3: R0002 | B3: Customer Support | C3: 3-5 yrs | D3: 4 | E3: 4 | F3: 5 | G3: 4 | H3: 4 | I3: 7 | J3: Flexible hours are very helpful.
A4: R0003 | B4: Technology | C4: 3-5 yrs | D4: 4 | E4: 4 | F4: 4 | G4: 3 | H4: 4 | I4: 8 | J4: My manager gives regular, useful feedback. Hybrid work helps me balance family.
A5: R0004 | B5: Operations | C5: 3-5 yrs | D5: 3 | E5: 3 | F5: 2 | G5: 2 | H5: 2 | I5: 4 | J5: We still use too many manual Excel reports. My manager rarely has time for one-on-ones.
A6: R0005 | B6: Technology | C6: <1 yr | D6: 4 | E6: 5 | F6: 5 | G6: 4 | H6: 4 | I6: 8 | J6: I was promoted on time and learnt a lot.
A7: R0006 | B7: Operations | C7: 5+ yrs | D7: 4 | E7: 4 | F7: 2 | G7: 3 | H7: 3 | I7: 7 | J7: Staff shortage means we do two people's work.
A8: R0007 | B8: Finance | C8: 5+ yrs | D8: 3 | E8: 3 | F8: 2 | G8: 3 | H8: 4 | I8: 7 | J8: Internal jobs go to outsiders first.
A9: R0008 | B9: Technology | C9: 1-3 yrs | D9: 2 | E9: 2 | F9: 3 | G9: 3 | H9: 4 | I9: 5 | J9: Increments did not match inflation this year. Feedback only comes during appraisal.
A10: R0009 | B10: Customer Support | C10: 3-5 yrs | D10: 2 | E10: 4 | F10: 3 | G10: 3 | H10: 4 | I10: 5 | J10: My manager rarely has time for one-on-ones.
A11: R0010 | B11: Customer Support | C11: <1 yr | D11: 3 | E11: 3 | F11: 3 | G11: 4 | H11: 2 | I11: 4 | J11: No clear promotion criteria.
A12: R0011 | B12: Finance | C12: 5+ yrs | D12: 2 | E12: 4 | F12: 3 | G12: 2 | H12: 2 | I12: 6 | J12: Leave approvals are very slow.
A13: R0012 | B13: Finance | C13: 5+ yrs | D13: 2 | E13: 3 | F13: 2 | G13: 2 | H13: 4 | I13: 5 | J13: Internal jobs go to outsiders first.
... A301: R0300 | B301: Technology | C301: <1 yr | D301: 4 | E301: 4 | F301: 4 | G301: 4 | H301: 3 | I301: 6 | J301: My manager gives regular, useful feedback. Deadlines are realistic in my team.

Sheet Gold Labels (evaluation)
A1: response_id | B1: true_themes | C1: true_tone
A2: R0001 | B2: Manager support | C2: Positive
A3: R0002 | B3: Flexibility | C3: Positive
A4: R0003 | B4: Manager support; Flexibility | C4: Positive
A5: R0004 | B5: Tools and systems; Manager support | C5: Negative
A6: R0005 | B6: Career growth | C6: Positive
A7: R0006 | B7: Workload | C7: Negative
A8: R0007 | B8: Career growth | C8: Negative
A9: R0008 | B9: Pay and benefits; Manager support | C9: Negative
A10: R0009 | B10: Manager support | C10: Negative
A11: R0010 | B11: Career growth | C11: Negative
A12: R0011 | B12: Flexibility | C12: Negative
... A301: R0300 | B301: Manager support; Workload | C301: Positive

Sheet Data Dictionary
A1: sheet | B1: column | C1: data_type | D1: example_value | E1: non_empty_values | F1: distinct_values
A2: Responses | B2: response_id | C2: Text | D2: R0001 | E2: 300 | F2: 300
A3: Responses | B3: department | C3: Text | D3: Technology | E3: 300 | F3: 6
A4: Responses | B4: tenure_band | C4: Text | D4: 3-5 yrs | E4: 300 | F4: 4
A5: Responses | B5: q1_clear_goals_1to5 | C5: Whole number | D5: 4 | E5: 300 | F5: 5
A6: Responses | B6: q2_manager_support_1to5 | C6: Whole number | D6: 4 | E6: 300 | F6: 5
A7: Responses | B7: q3_fair_pay_1to5 | C7: Whole number | D7: 5 | E7: 300 | F7: 5
A8: Responses | B8: q4_growth_1to5 | C8: Whole number | D8: 3 | E8: 300 | F8: 5
A9: Responses | B9: q5_worklife_balance_1to5 | C9: Whole number | D9: 5 | E9: 300 | F9: 5
A10: Responses | B10: enps_0to10 | C10: Whole number | D10: 8 | E10: 300 | F10: 10
A11: Responses | B11: open_comment | C11: Text | D11: My manager gives regular, useful feedback. | E11: 300 | F11: 130
A12: Gold Labels (evaluation) | B12: response_id | C12: Text | D12: R0001 | E12: 300 | F12: 300
A13: Gold Labels (evaluation) | B13: true_themes | C13: Text | D13: Manager support | E13: 300 | F13: 36
A14: Gold Labels (evaluation) | B14: true_tone | C14: Text | D14: Positive | E14: 300 | F14: 2

Sheet AI Use Log
A1: AI Use Log - fill one row per prompt (minimum 15). Yellow cells are for you to fill; row 4 is an example.
A2: Evidence = shared chat link or screenshot file name. Keep rejected outputs too - they earn marks under 'Prompting and iteration'.
A3: # | B3: date | C3: tool | D3: model / mode | E3: settings used (if any) | F3: prompt (exact text) | G3: what the output did well / badly | H3: what I changed next and why | I3: kept or rejected | J3: evidence link / file
A4: 1 | B4: 46034 | C4: Gemini (free) | D4: Gemini app, default | E4: - | F4: You are a business analyst. Using the attached sheet for 'Employee survey theme coder', list the first 3 steps to build it and what could go wrong. | G4: Clear steps, but assumed a column that does not exist | H4: Told it the exact column names and asked it to recheck | I4: Rejected | J4: screenshot_01.png
A5: 2 | C5: 46298 | D5: ChatGPT | E5: GPT-5.6 Luna / Instant | F5: Role: You are a business analyst. Task: Read my file and list the first 5 steps to sort the open comments into themes. Also say what could go wrong. Context: The file has 300 employee survey rows. The columns are response_id, department, tenure_band, q1 to q5 scores, enps_0to10 and open_comment. Format: A numbered list in easy English. Rules: Use only the real column names. Do not guess any column. | G5: Gave 5 clear steps, each with a 'what could go wrong' line. Used the real column open_comment. It stayed general and did not name themes yet. | H5: Nothing to fix. Moved on to asking for themes. | I5: Kept | J5: screenshot_01.png | K5: https://drive.google.com/drive/folders/1FOJGQqnoX1TA6cijtuTd0_0EwIaO9OU9?usp=sharing
A6: 3 | C6: 46298 | D6: ChatGPT | E6: GPT-5.6 Luna / Instant | F6: Role: You are an HR researcher. Task: Read all open_comment values and suggest 6 themes. Context: This is an employee engagement survey. Format: A table with theme name, short meaning, and 2 example comments. Rules: Themes must not overlap. Use only comments from the file. | G6: Gave 6 themes (Manager support, Flexibility, Workload, Tools and systems, Pay and benefits, Career growth) with 2 real example comments each. Themes mostly do not overlap. It also warned that one comment can have more than one issue. | H6: Used these 6 themes as the base for the codebook. | I6: Kept | J6: screenshot_02.png
A7: 4 | C7: 46298 | D7: ChatGPT | E7: GPT-5.6 Luna / Instant | F7: Role: You are an expert in survey coding. Task: Turn these themes into a codebook: [paste themes]. Context: I will use it to code 300 comments. Format: A table with theme, meaning, "code it when", "do not code it when", and 3 keywords. Rules: Keep the words simple. Give each theme a different meaning. | G7: Made a table with meaning, 'code it when', 'do not code it when' and 3 keywords for each theme, in easy words. But it had no rule for comments with two themes and no rule for tone. I also left the placeholder [paste themes] in the prompt; it still worked because the themes were already in the chat. | H7: Wrote a new prompt to add rules for two-theme comments and tone, because this codebook was not enough to code 300 comments in the same way. | I7: Kept, then improved (see next row) | J7: screenshot_03.png
A8: 5 | C8: 46298 | D8: ChatGPT | E8: GPT-5.6 Luna / Instant | F8: Role: You are a survey coding expert. Task: Add clear rules to the above codebook for comments with two ideas and for tone Context: Some comments have two sentences. One can be good and one bad. Format: A short list of rules, then the final codebook. Rules: Use easy words. Give one example for each rule. | G8: IMPROVEMENT ROUND 1 (codebook). Added 7 short rules with one example each (two themes allowed, no loose second theme, how to decide tone) and gave the final codebook. But it added 'Mixed' and 'Neutral' tone options, and my coding prompts only allow Positive or Negative. | H8: Kept the theme rules. In the coding prompts I told it tone is only Positive or Negative. | I8: Kept | J8: screenshot_04.png
A9: 6 | C9: 46298 | D9: ChatGPT | E9: GPT-5.6 Luna / Instant | F9: Role: You are a careful coder. Task: Code each comment using my codebook Context: A comment can have one or two themes. Tone is Positive or Negative. Format: A table with response_id, themes (separated by ";"), tone. Rules: Use only theme names from the codebook. Do not explain. | G9: Coded the 30 test rows in the right table format with no explanation. But 2 rows had an empty themes cell (R0011 and R0017), so the output was not complete. | H9: IMPROVEMENT ROUND 2 (blank themes). Added a new rule to the next prompts: 'Dont miss any theme blank use the one which suits the best', so every row gets a theme. | I9: Partly rejected: blank rows not accepted, prompt re-sent with a stricter rule | J9: screenshot_05.png
A10: 7 | C10: 46298 | D10: ChatGPT | E10: GPT-5.6 Luna / Instant | F10: Role: You are a careful coder. Task: Code all 100 comments using the final codebook Format: A table with response_id, themes (separated by ";"), tone. Rules: Keep the same order as the file. Use only codebook theme names. Do not skip any row. Dont miss any theme blank use the one which suits the best | G10: Coded rows 001-100 in the same format. No blank themes in the rows I could see. Tone is only Positive or Negative. | H10: Used the same prompt for the next two batches. | I10: Kept | J10: screenshot_06.png
A11: 8 | C11: 46298 | D11: ChatGPT | E11: GPT-5.6 Luna / Instant | F11: Role: You are a careful coder. Task: Code all 100 comments using the final codebook Format: A table with response_id, themes (separated by ";"), tone. Rules: Keep the same order as the file. Use only codebook theme names. Do not skip any row. Dont miss any theme blank use the one which suits the best | G11: Coded rows 101-200 in the same format. No blank themes in the rows I could see. Tone is only Positive or Negative. | H11: No change. Used the same prompt for rows 201-300. | I11: Kept | J11: screenshot_07.png
A12: 9 | C12: 46298 | D12: ChatGPT | E12: GPT-5.6 Luna / Instant | F12: Role: You are a careful coder. Task: Code all 100 comments using the final codebook Format: A table with response_id, themes (separated by ";"), tone. Rules: Keep the same order as the file. Use only codebook theme names. Do not skip any row. Dont miss any theme blank use the one which suits the best | G12: Coded rows 201-300 in the same format with no blank themes in the rows I could see. | H12: Asked it to put all three batches into one Excel file. | I12: Kept | J12: screenshot_08.png
A13: 10 | C13: 46298 | D13: ChatGPT | E13: GPT-5.6 Luna / Instant | F13: Attach all the outputs from 1-300 to 1 excel file | G13: Combined R0001-R0300 into one Excel file with response_id, themes and tone. Fast, but I must not trust the row count until it is checked. | H13: Ran a checking prompt on the file next. | I13: Kept | J13: screenshot_09.png
A14: 11 | C14: 46298 | D14: ChatGPT | E14: GPT-5.6 Luna / Instant | F14: Role: You are a data checker. Task: Check my coded file for problems. Context: It should have 300 rows. Every row should have themes and tone filled in. Format: A short list: total rows, empty cells, and any theme name that is not in my codebook. Rules: Do not change my data. Only report what you find. | G14: Reported 300 rows, 0 empty theme cells, 0 empty tone cells and no theme name outside the codebook. Short and clear. It only checks that the file is complete, not that the codes are correct. | H14: Nothing to fix. Moved on to counting themes. Correctness is checked separately with the 50-row gold check. | I14: Kept | J14: screenshot_10.png
A15: 12 | C15: 46298 | D15: ChatGPT | E15: GPT-5.6 Luna / Instant | F15: Role: You are a data analyst. Task: Count how many comments each theme has. Split each theme into Positive and Negative. Format: One small table with a total row. Rules: Tell me how to check the total in Excel. The theme counts can add up to more than 300 because some comments have two themes. | G15: Gave a table with Positive, Negative and Total for each theme (Positive 203, Negative 248, Total 451) and explained why the total is more than 300. Also gave Excel COUNTIFS formulas so I can check it. | H15: Used the same file to count by department next. | I15: Kept | J15: screenshot_11.png
A16: 13 | C16: 46298 | D16: ChatGPT | E16: GPT-5.6 Luna / Instant | F16: Role: You are a data analyst. Task: Show how many comments each department has for each theme. Say which department has the most Negative comments. Format: A table with departments as rows and themes as columns, then 2 simple sentences. Rules: Use only my file. Show the total so I can check it. | G16: Gave a department-by-theme table with total 451. It said Operations has the most Negative comments (32). But the table shows all comments, not only Negative ones, so the 32 is not visible in the table. | H16: Asked it to add the tables to the Excel file. I will check the Operations Negative count in Excel myself. | I16: Kept, but the Operations claim needs a manual check | J16: screenshot_12.png
A17: 14 | C17: 46298 | D17: ChatGPT | E17: GPT-5.6 Luna / Instant | F17: add this table and the above prompts to the excel sheet you gave me | G17: Created T38_Coded_Comments_1-300_Complete.xlsx with the sheets Coded Comments, Theme Counts, Department x Theme Counts and Prompts. Did what I asked. | H17: Kept adding the next analysis to the same file. | I17: Kept | J17: screenshot_13.png
... A24: 21 | C24: 46298 | D24: ChatGPT | E24: GPT-5.6 Luna / Instant | F24: Remove things which are done twice | G24: Removed the duplicate and older sheets and kept the latest versions. The final workbook has 9 sheets. I still need to open it and check that no needed sheet was deleted. | H24: Next: open the final workbook, check the sheets, and copy the final tables into my submission workbook. | I24: Kept | J24: screenshot_20.png
A25: 22 | C25: 46298 | D25: ChatGPT | E25: GPT-5.6 Luna / Instant | F25: Role: You are a web developer. Task: Make one HTML file for an employee survey dashboard. First it must ask me to upload my Excel file. Then it must show charts and a guide for the manager. Context: My file has 300 rows. The columns are department, tenure_band, q1 to q5 (scores from 1 to 5), enps_0to10, open_comment, themes and tone. Tone is Positive or Negative. A score of 1 or 2 is low. Manager support goes with q2, Pay and benefits with q3, Career growth with q4, Flexibility and Workload with q5, Tools and systems with q1. Format: - Number cards: total responses, eNPS, % Negative comments, average score - Charts: themes by tone, average score for q1 to q5, eNPS by department, department by theme heatmap - Filters for department and tenure_band - A "Manager decision guide" with the top 3 problems, the numbers, and one simple action for each Rules: Use one file only. Use Chart.js and SheetJS from a CDN. Use easy English. Use only my file's data, do not make up numbers. | G25: Made one HTML file, employee_survey_dashboard.html. | I25: Kept | J25: screenshot_21.png

Sheet Codebook
A1: theme | B1: meaning | C1: code it when | D1: do not code it when | E1: 3 keywords
A2: Manager support | B2: Help, feedback, communication, support from manager. | C2: Code for manager feedback, one-to-ones, guidance, manager availability. | D2: Do not code if only pay/workload/career growth without manager support. | E2: manager, feedback, support
A3: Flexibility | B3: When/where employee works. | C3: Code flexible hours, hybrid, remote, office attendance. | D3: Do not code workload/long hours without flexibility. | E3: flexible, hybrid, remote
A4: Workload | B4: Amount/pressure of work. | C4: Code too much work, staff shortages, deadlines, long hours, too many projects. | D4: Do not code other issues with no clear workload point. | E4: workload, deadlines, overtime
A5: Tools and systems | B5: Technology/systems used to work. | C5: Code software, systems, laptops, CRM, reports, crashes, slow systems. | D5: Do not code workload/staffing without tool/system. | E5: systems, software, CRM
A6: Pay and benefits | B6: Money/salary/increments/benefits. | C6: Code salary, increments, pay, insurance, benefits. | D6: Do not code only promotion/career opportunities. | E6: salary, pay, benefits
A7: Career growth | B7: Development/progression. | C7: Code promotion, career paths, promotion criteria, learning, internal opportunities. | D7: Do not code only salary, manager support, workload. | E7: promotion, career, growth
A9: Coding rules
A10: 1. Use one theme when the comment clearly discusses one theme.
A11: 2. Use two themes only when the comment clearly contains two distinct theme ideas.
A12: 3. Separate two themes using ';'.
A13: 4. Do not add a second theme just because it is loosely related.
A14: 5. Code each sentence separately if needed.
A15: 6. Tone is for the whole comment: Positive or Negative.
A16: 7. Do not decide tone from one word only; consider the whole comment.
A17: 8. For a two-theme comment, use one overall tone.

Sheet Coded Responses
A1: response_id | B1: department | C1: tenure_band | D1: q1_clear_goals_1to5 | E1: q2_manager_support_1to5 | F1: q3_fair_pay_1to5 | G1: q4_growth_1to5 | H1: q5_worklife_balance_1to5 | I1: enps_0to10 | J1: open_comment | K1: themes | L1: tone | M1: helper: Manager support | N1: helper: Flexibility | O1: helper: Workload | P1: helper: Tools and systems | Q1: helper: Pay and benefits | R1: helper: Career growth
A2: R0001 | B2: Technology | C2: 3-5 yrs | D2: 4 | E2: 4 | F2: 5 | G2: 3 | H2: 5 | I2: 8 | J2: My manager gives regular, useful feedback. | K2: Manager support | L2: Positive | M2: =IF(AND(ISNUMBER(SEARCH("Manager support",K2)),L2="Negative"),"Manager support Negative","Everyone else") -> Everyone else | N2: =IF(AND(ISNUMBER(SEARCH("Flexibility",K2)),L2="Negative"),"Flexibility Negative","Everyone else") -> Everyone else | O2: =IF(AND(ISNUMBER(SEARCH("Workload",K2)),L2="Negative"),"Workload Negative","Everyone else") -> Everyone else | P2: =IF(AND(ISNUMBER(SEARCH("Tools and systems",K2)),L2="Negative"),"Tools and systems Negative","Everyone else") -> Everyone else | Q2: =IF(AND(ISNUMBER(SEARCH("Pay and benefits",K2)),L2="Negative"),"Pay and benefits Negative","Everyone else") -> Everyone else | R2: =IF(AND(ISNUMBER(SEARCH("Career growth",K2)),L2="Negative"),"Career growth Negative","Everyone else") -> Everyone else
A3: R0002 | B3: Customer Support | C3: 3-5 yrs | D3: 4 | E3: 4 | F3: 5 | G3: 4 | H3: 4 | I3: 7 | J3: Flexible hours are very helpful. | K3: Flexibility | L3: Positive | M3: =IF(AND(ISNUMBER(SEARCH("Manager support",K3)),L3="Negative"),"Manager support Negative","Everyone else") -> Everyone else | N3: =IF(AND(ISNUMBER(SEARCH("Flexibility",K3)),L3="Negative"),"Flexibility Negative","Everyone else") -> Everyone else | O3: =IF(AND(ISNUMBER(SEARCH("Workload",K3)),L3="Negative"),"Workload Negative","Everyone else") -> Everyone else | P3: =IF(AND(ISNUMBER(SEARCH("Tools and systems",K3)),L3="Negative"),"Tools and systems Negative","Everyone else") -> Everyone else | Q3: =IF(AND(ISNUMBER(SEARCH("Pay and benefits",K3)),L3="Negative"),"Pay and benefits Negative","Everyone else") -> Everyone else | R3: =IF(AND(ISNUMBER(SEARCH("Career growth",K3)),L3="Negative"),"Career growth Negative","Everyone else") -> Everyone else
A4: R0003 | B4: Technology | C4: 3-5 yrs | D4: 4 | E4: 4 | F4: 4 | G4: 3 | H4: 4 | I4: 8 | J4: My manager gives regular, useful feedback. Hybrid work helps me balance family. | K4: Manager support; Flexibility | L4: Positive | M4: =IF(AND(ISNUMBER(SEARCH("Manager support",K4)),L4="Negative"),"Manager support Negative","Everyone else") -> Everyone else | N4: =IF(AND(ISNUMBER(SEARCH("Flexibility",K4)),L4="Negative"),"Flexibility Negative","Everyone else") -> Everyone else | O4: =IF(AND(ISNUMBER(SEARCH("Workload",K4)),L4="Negative"),"Workload Negative","Everyone else") -> Everyone else | P4: =IF(AND(ISNUMBER(SEARCH("Tools and systems",K4)),L4="Negative"),"Tools and systems Negative","Everyone else") -> Everyone else | Q4: =IF(AND(ISNUMBER(SEARCH("Pay and benefits",K4)),L4="Negative"),"Pay and benefits Negative","Everyone else") -> Everyone else | R4: =IF(AND(ISNUMBER(SEARCH("Career growth",K4)),L4="Negative"),"Career growth Negative","Everyone else") -> Everyone else
A5: R0004 | B5: Operations | C5: 3-5 yrs | D5: 3 | E5: 3 | F5: 2 | G5: 2 | H5: 2 | I5: 4 | J5: We still use too many manual Excel reports. My manager rarely has time for one-on-ones. | K5: Tools and systems; Manager support | L5: Negative | M5: =IF(AND(ISNUMBER(SEARCH("Manager support",K5)),L5="Negative"),"Manager support Negative","Everyone else") -> Manager support Negative | N5: =IF(AND(ISNUMBER(SEARCH("Flexibility",K5)),L5="Negative"),"Flexibility Negative","Everyone else") -> Everyone else | O5: =IF(AND(ISNUMBER(SEARCH("Workload",K5)),L5="Negative"),"Workload Negative","Everyone else") -> Everyone else | P5: =IF(AND(ISNUMBER(SEARCH("Tools and systems",K5)),L5="Negative"),"Tools and systems Negative","Everyone else") -> Tools and systems Negative | Q5: =IF(AND(ISNUMBER(SEARCH("Pay and benefits",K5)),L5="Negative"),"Pay and benefits Negative","Everyone else") -> Everyone else | R5: =IF(AND(ISNUMBER(SEARCH("Career growth",K5)),L5="Negative"),"Career growth Negative","Everyone else") -> Everyone else
A6: R0005 | B6: Technology | C6: <1 yr | D6: 4 | E6: 5 | F6: 5 | G6: 4 | H6: 4 | I6: 8 | J6: I was promoted on time and learnt a lot. | K6: Career growth | L6: Positive | M6: =IF(AND(ISNUMBER(SEARCH("Manager support",K6)),L6="Negative"),"Manager support Negative","Everyone else") -> Everyone else | N6: =IF(AND(ISNUMBER(SEARCH("Flexibility",K6)),L6="Negative"),"Flexibility Negative","Everyone else") -> Everyone else | O6: =IF(AND(ISNUMBER(SEARCH("Workload",K6)),L6="Negative"),"Workload Negative","Everyone else") -> Everyone else | P6: =IF(AND(ISNUMBER(SEARCH("Tools and systems",K6)),L6="Negative"),"Tools and systems Negative","Everyone else") -> Everyone else | Q6: =IF(AND(ISNUMBER(SEARCH("Pay and benefits",K6)),L6="Negative"),"Pay and benefits Negative","Everyone else") -> Everyone else | R6: =IF(AND(ISNUMBER(SEARCH("Career growth",K6)),L6="Negative"),"Career growth Negative","Everyone else") -> Everyone else
A7: R0006 | B7: Operations | C7: 5+ yrs | D7: 4 | E7: 4 | F7: 2 | G7: 3 | H7: 3 | I7: 7 | J7: Staff shortage means we do two people's work. | K7: Workload | L7: Negative | M7: =IF(AND(ISNUMBER(SEARCH("Manager support",K7)),L7="Negative"),"Manager support Negative","Everyone else") -> Everyone else | N7: =IF(AND(ISNUMBER(SEARCH("Flexibility",K7)),L7="Negative"),"Flexibility Negative","Everyone else") -> Everyone else | O7: =IF(AND(ISNUMBER(SEARCH("Workload",K7)),L7="Negative"),"Workload Negative","Everyone else") -> Workload Negative | P7: =IF(AND(ISNUMBER(SEARCH("Tools and systems",K7)),L7="Negative"),"Tools and systems Negative","Everyone else") -> Everyone else | Q7: =IF(AND(ISNUMBER(SEARCH("Pay and benefits",K7)),L7="Negative"),"Pay and benefits Negative","Everyone else") -> Everyone else | R7: =IF(AND(ISNUMBER(SEARCH("Career growth",K7)),L7="Negative"),"Career growth Negative","Everyone else") -> Everyone else
A8: R0007 | B8: Finance | C8: 5+ yrs | D8: 3 | E8: 3 | F8: 2 | G8: 3 | H8: 4 | I8: 7 | J8: Internal jobs go to outsiders first. | K8: Career growth | L8: Negative | M8: =IF(AND(ISNUMBER(SEARCH("Manager support",K8)),L8="Negative"),"Manager support Negative","Everyone else") -> Everyone else | N8: =IF(AND(ISNUMBER(SEARCH("Flexibility",K8)),L8="Negative"),"Flexibility Negative","Everyone else") -> Everyone else | O8: =IF(AND(ISNUMBER(SEARCH("Workload",K8)),L8="Negative"),"Workload Negative","Everyone else") -> Everyone else | P8: =IF(AND(ISNUMBER(SEARCH("Tools and systems",K8)),L8="Negative"),"Tools and systems Negative","Everyone else") -> Everyone else | Q8: =IF(AND(ISNUMBER(SEARCH("Pay and benefits",K8)),L8="Negative"),"Pay and benefits Negative","Everyone else") -> Everyone else | R8: =IF(AND(ISNUMBER(SEARCH("Career growth",K8)),L8="Negative"),"Career growth Negative","Everyone else") -> Career growth Negative
A9: R0008 | B9: Technology | C9: 1-3 yrs | D9: 2 | E9: 2 | F9: 3 | G9: 3 | H9: 4 | I9: 5 | J9: Increments did not match inflation this year. Feedback only comes during appraisal. | K9: Pay and benefits; Manager support | L9: Negative | M9: =IF(AND(ISNUMBER(SEARCH("Manager support",K9)),L9="Negative"),"Manager support Negative","Everyone else") -> Manager support Negative | N9: =IF(AND(ISNUMBER(SEARCH("Flexibility",K9)),L9="Negative"),"Flexibility Negative","Everyone else") -> Everyone else | O9: =IF(AND(ISNUMBER(SEARCH("Workload",K9)),L9="Negative"),"Workload Negative","Everyone else") -> Everyone else | P9: =IF(AND(ISNUMBER(SEARCH("Tools and systems",K9)),L9="Negative"),"Tools and systems Negative","Everyone else") -> Everyone else | Q9: =IF(AND(ISNUMBER(SEARCH("Pay and benefits",K9)),L9="Negative"),"Pay and benefits Negative","Everyone else") -> Pay and benefits Negative | R9: =IF(AND(ISNUMBER(SEARCH("Career growth",K9)),L9="Negative"),"Career growth Negative","Everyone else") -> Everyone else
A10: R0009 | B10: Customer Support | C10: 3-5 yrs | D10: 2 | E10: 4 | F10: 3 | G10: 3 | H10: 4 | I10: 5 | J10: My manager rarely has time for one-on-ones. | K10: Manager support | L10: Negative | M10: =IF(AND(ISNUMBER(SEARCH("Manager support",K10)),L10="Negative"),"Manager support Negative","Everyone else") -> Manager support Negative | N10: =IF(AND(ISNUMBER(SEARCH("Flexibility",K10)),L10="Negative"),"Flexibility Negative","Everyone else") -> Everyone else | O10: =IF(AND(ISNUMBER(SEARCH("Workload",K10)),L10="Negative"),"Workload Negative","Everyone else") -> Everyone else | P10: =IF(AND(ISNUMBER(SEARCH("Tools and systems",K10)),L10="Negative"),"Tools and systems Negative","Everyone else") -> Everyone else | Q10: =IF(AND(ISNUMBER(SEARCH("Pay and benefits",K10)),L10="Negative"),"Pay and benefits Negative","Everyone else") -> Everyone else | R10: =IF(AND(ISNUMBER(SEARCH("Career growth",K10)),L10="Negative"),"Career growth Negative","Everyone else") -> Everyone else
A11: R0010 | B11: Customer Support | C11: <1 yr | D11: 3 | E11: 3 | F11: 3 | G11: 4 | H11: 2 | I11: 4 | J11: No clear promotion criteria. | K11: Career growth | L11: Negative | M11: =IF(AND(ISNUMBER(SEARCH("Manager support",K11)),L11="Negative"),"Manager support Negative","Everyone else") -> Everyone else | N11: =IF(AND(ISNUMBER(SEARCH("Flexibility",K11)),L11="Negative"),"Flexibility Negative","Everyone else") -> Everyone else | O11: =IF(AND(ISNUMBER(SEARCH("Workload",K11)),L11="Negative"),"Workload Negative","Everyone else") -> Everyone else | P11: =IF(AND(ISNUMBER(SEARCH("Tools and systems",K11)),L11="Negative"),"Tools and systems Negative","Everyone else") -> Everyone else | Q11: =IF(AND(ISNUMBER(SEARCH("Pay and benefits",K11)),L11="Negative"),"Pay and benefits Negative","Everyone else") -> Everyone else | R11: =IF(AND(ISNUMBER(SEARCH("Career growth",K11)),L11="Negative"),"Career growth Negative","Everyone else") -> Career growth Negative
A12: R0011 | B12: Finance | C12: 5+ yrs | D12: 2 | E12: 4 | F12: 3 | G12: 2 | H12: 2 | I12: 6 | J12: Leave approvals are very slow. | K12: Flexibility | L12: Negative | M12: =IF(AND(ISNUMBER(SEARCH("Manager support",K12)),L12="Negative"),"Manager support Negative","Everyone else") -> Everyone else | N12: =IF(AND(ISNUMBER(SEARCH("Flexibility",K12)),L12="Negative"),"Flexibility Negative","Everyone else") -> Flexibility Negative | O12: =IF(AND(ISNUMBER(SEARCH("Workload",K12)),L12="Negative"),"Workload Negative","Everyone else") -> Everyone else | P12: =IF(AND(ISNUMBER(SEARCH("Tools and systems",K12)),L12="Negative"),"Tools and systems Negative","Everyone else") -> Everyone else | Q12: =IF(AND(ISNUMBER(SEARCH("Pay and benefits",K12)),L12="Negative"),"Pay and benefits Negative","Everyone else") -> Everyone else | R12: =IF(AND(ISNUMBER(SEARCH("Career growth",K12)),L12="Negative"),"Career growth Negative","Everyone else") -> Everyone else
A13: R0012 | B13: Finance | C13: 5+ yrs | D13: 2 | E13: 3 | F13: 2 | G13: 2 | H13: 4 | I13: 5 | J13: Internal jobs go to outsiders first. | K13: Career growth | L13: Negative | M13: =IF(AND(ISNUMBER(SEARCH("Manager support",K13)),L13="Negative"),"Manager support Negative","Everyone else") -> Everyone else | N13: =IF(AND(ISNUMBER(SEARCH("Flexibility",K13)),L13="Negative"),"Flexibility Negative","Everyone else") -> Everyone else | O13: =IF(AND(ISNUMBER(SEARCH("Workload",K13)),L13="Negative"),"Workload Negative","Everyone else") -> Everyone else | P13: =IF(AND(ISNUMBER(SEARCH("Tools and systems",K13)),L13="Negative"),"Tools and systems Negative","Everyone else") -> Everyone else | Q13: =IF(AND(ISNUMBER(SEARCH("Pay and benefits",K13)),L13="Negative"),"Pay and benefits Negative","Everyone else") -> Everyone else | R13: =IF(AND(ISNUMBER(SEARCH("Career growth",K13)),L13="Negative"),"Career growth Negative","Everyone else") -> Career growth Negative
... A301: R0300 | B301: Technology | C301: <1 yr | D301: 4 | E301: 4 | F301: 4 | G301: 4 | H301: 3 | I301: 6 | J301: My manager gives regular, useful feedback. Deadlines are realistic in my team. | K301: Manager support; Workload | L301: Positive | M301: =IF(AND(ISNUMBER(SEARCH("Manager support",K301)),L301="Negative"),"Manager support Negative","Everyone else") -> Everyone else | N301: =IF(AND(ISNUMBER(SEARCH("Flexibility",K301)),L301="Negative"),"Flexibility Negative","Everyone else") -> Everyone else | O301: =IF(AND(ISNUMBER(SEARCH("Workload",K301)),L301="Negative"),"Workload Negative","Everyone else") -> Everyone else | P301: =IF(AND(ISNUMBER(SEARCH("Tools and systems",K301)),L301="Negative"),"Tools and systems Negative","Everyone else") -> Everyone else | Q301: =IF(AND(ISNUMBER(SEARCH("Pay and benefits",K301)),L301="Negative"),"Pay and benefits Negative","Everyone else") -> Everyone else | R301: =IF(AND(ISNUMBER(SEARCH("Career growth",K301)),L301="Negative"),"Career growth Negative","Everyone else") -> Everyone else

Sheet Theme Counts
A1: Theme | B1: Positive | C1: Negative | D1: Total
A2: Manager support | B2: =COUNTIFS('Coded Responses'!$K$2:$K$301,"*"&$A2&"*",'Coded Responses'!$L$2:$L$301,B$1) -> 38 | C2: =COUNTIFS('Coded Responses'!$K$2:$K$301,"*"&$A2&"*",'Coded Responses'!$L$2:$L$301,C$1) -> 45 | D2: =SUM(B2:C2) -> 83
A3: Flexibility | B3: =COUNTIFS('Coded Responses'!$K$2:$K$301,"*"&$A3&"*",'Coded Responses'!$L$2:$L$301,B$1) -> 31 | C3: =COUNTIFS('Coded Responses'!$K$2:$K$301,"*"&$A3&"*",'Coded Responses'!$L$2:$L$301,C$1) -> 49 | D3: =SUM(B3:C3) -> 80
A4: Workload | B4: =COUNTIFS('Coded Responses'!$K$2:$K$301,"*"&$A4&"*",'Coded Responses'!$L$2:$L$301,B$1) -> 38 | C4: =COUNTIFS('Coded Responses'!$K$2:$K$301,"*"&$A4&"*",'Coded Responses'!$L$2:$L$301,C$1) -> 40 | D4: =SUM(B4:C4) -> 78
A5: Tools and systems | B5: =COUNTIFS('Coded Responses'!$K$2:$K$301,"*"&$A5&"*",'Coded Responses'!$L$2:$L$301,B$1) -> 31 | C5: =COUNTIFS('Coded Responses'!$K$2:$K$301,"*"&$A5&"*",'Coded Responses'!$L$2:$L$301,C$1) -> 41 | D5: =SUM(B5:C5) -> 72
A6: Pay and benefits | B6: =COUNTIFS('Coded Responses'!$K$2:$K$301,"*"&$A6&"*",'Coded Responses'!$L$2:$L$301,B$1) -> 34 | C6: =COUNTIFS('Coded Responses'!$K$2:$K$301,"*"&$A6&"*",'Coded Responses'!$L$2:$L$301,C$1) -> 38 | D6: =SUM(B6:C6) -> 72
A7: Career growth | B7: =COUNTIFS('Coded Responses'!$K$2:$K$301,"*"&$A7&"*",'Coded Responses'!$L$2:$L$301,B$1) -> 31 | C7: =COUNTIFS('Coded Responses'!$K$2:$K$301,"*"&$A7&"*",'Coded Responses'!$L$2:$L$301,C$1) -> 35 | D7: =SUM(B7:C7) -> 66
A8: Total | B8: =SUM(B2:B7) -> 203 | C8: =SUM(C2:C7) -> 248 | D8: =SUM(D2:D7) -> 451
A9: Totals are more than 300 because some comments have two themes.
A11: Theme counts by department
A12: Department | B12: Manager support | C12: Flexibility | D12: Workload | E12: Tools and systems | F12: Pay and benefits | G12: Career growth | H12: Total
A13: Customer Support | B13: =COUNTIFS('Coded Responses'!$B$2:$B$301,$A13,'Coded Responses'!$K$2:$K$301,"*"&B$12&"*") -> 13 | C13: =COUNTIFS('Coded Responses'!$B$2:$B$301,$A13,'Coded Responses'!$K$2:$K$301,"*"&C$12&"*") -> 15 | D13: =COUNTIFS('Coded Responses'!$B$2:$B$301,$A13,'Coded Responses'!$K$2:$K$301,"*"&D$12&"*") -> 12 | E13: =COUNTIFS('Coded Responses'!$B$2:$B$301,$A13,'Coded Responses'!$K$2:$K$301,"*"&E$12&"*") -> 10 | F13: =COUNTIFS('Coded Responses'!$B$2:$B$301,$A13,'Coded Responses'!$K$2:$K$301,"*"&F$12&"*") -> 11 | G13: =COUNTIFS('Coded Responses'!$B$2:$B$301,$A13,'Coded Responses'!$K$2:$K$301,"*"&G$12&"*") -> 11 | H13: =SUM(B13:G13) -> 72
A14: Finance | B14: =COUNTIFS('Coded Responses'!$B$2:$B$301,$A14,'Coded Responses'!$K$2:$K$301,"*"&B$12&"*") -> 9 | C14: =COUNTIFS('Coded Responses'!$B$2:$B$301,$A14,'Coded Responses'!$K$2:$K$301,"*"&C$12&"*") -> 12 | D14: =COUNTIFS('Coded Responses'!$B$2:$B$301,$A14,'Coded Responses'!$K$2:$K$301,"*"&D$12&"*") -> 17 | E14: =COUNTIFS('Coded Responses'!$B$2:$B$301,$A14,'Coded Responses'!$K$2:$K$301,"*"&E$12&"*") -> 12 | F14: =COUNTIFS('Coded Responses'!$B$2:$B$301,$A14,'Coded Responses'!$K$2:$K$301,"*"&F$12&"*") -> 16 | G14: =COUNTIFS('Coded Responses'!$B$2:$B$301,$A14,'Coded Responses'!$K$2:$K$301,"*"&G$12&"*") -> 12 | H14: =SUM(B14:G14) -> 78
A15: HR | B15: =COUNTIFS('Coded Responses'!$B$2:$B$301,$A15,'Coded Responses'!$K$2:$K$301,"*"&B$12&"*") -> 18 | C15: =COUNTIFS('Coded Responses'!$B$2:$B$301,$A15,'Coded Responses'!$K$2:$K$301,"*"&C$12&"*") -> 9 | D15: =COUNTIFS('Coded Responses'!$B$2:$B$301,$A15,'Coded Responses'!$K$2:$K$301,"*"&D$12&"*") -> 11 | E15: =COUNTIFS('Coded Responses'!$B$2:$B$301,$A15,'Coded Responses'!$K$2:$K$301,"*"&E$12&"*") -> 10 | F15: =COUNTIFS('Coded Responses'!$B$2:$B$301,$A15,'Coded Responses'!$K$2:$K$301,"*"&F$12&"*") -> 11 | G15: =COUNTIFS('Coded Responses'!$B$2:$B$301,$A15,'Coded Responses'!$K$2:$K$301,"*"&G$12&"*") -> 12 | H15: =SUM(B15:G15) -> 71
A16: Operations | B16: =COUNTIFS('Coded Responses'!$B$2:$B$301,$A16,'Coded Responses'!$K$2:$K$301,"*"&B$12&"*") -> 11 | C16: =COUNTIFS('Coded Responses'!$B$2:$B$301,$A16,'Coded Responses'!$K$2:$K$301,"*"&C$12&"*") -> 13 | D16: =COUNTIFS('Coded Responses'!$B$2:$B$301,$A16,'Coded Responses'!$K$2:$K$301,"*"&D$12&"*") -> 11 | E16: =COUNTIFS('Coded Responses'!$B$2:$B$301,$A16,'Coded Responses'!$K$2:$K$301,"*"&E$12&"*") -> 15 | F16: =COUNTIFS('Coded Responses'!$B$2:$B$301,$A16,'Coded Responses'!$K$2:$K$301,"*"&F$12&"*") -> 11 | G16: =COUNTIFS('Coded Responses'!$B$2:$B$301,$A16,'Coded Responses'!$K$2:$K$301,"*"&G$12&"*") -> 10 | H16: =SUM(B16:G16) -> 71
A17: Sales | B17: =COUNTIFS('Coded Responses'!$B$2:$B$301,$A17,'Coded Responses'!$K$2:$K$301,"*"&B$12&"*") -> 15 | C17: =COUNTIFS('Coded Responses'!$B$2:$B$301,$A17,'Coded Responses'!$K$2:$K$301,"*"&C$12&"*") -> 16 | D17: =COUNTIFS('Coded Responses'!$B$2:$B$301,$A17,'Coded Responses'!$K$2:$K$301,"*"&D$12&"*") -> 13 | E17: =COUNTIFS('Coded Responses'!$B$2:$B$301,$A17,'Coded Responses'!$K$2:$K$301,"*"&E$12&"*") -> 12 | F17: =COUNTIFS('Coded Responses'!$B$2:$B$301,$A17,'Coded Responses'!$K$2:$K$301,"*"&F$12&"*") -> 13 | G17: =COUNTIFS('Coded Responses'!$B$2:$B$301,$A17,'Coded Responses'!$K$2:$K$301,"*"&G$12&"*") -> 12 | H17: =SUM(B17:G17) -> 81
A18: Technology | B18: =COUNTIFS('Coded Responses'!$B$2:$B$301,$A18,'Coded Responses'!$K$2:$K$301,"*"&B$12&"*") -> 17 | C18: =COUNTIFS('Coded Responses'!$B$2:$B$301,$A18,'Coded Responses'!$K$2:$K$301,"*"&C$12&"*") -> 15 | D18: =COUNTIFS('Coded Responses'!$B$2:$B$301,$A18,'Coded Responses'!$K$2:$K$301,"*"&D$12&"*") -> 14 | E18: =COUNTIFS('Coded Responses'!$B$2:$B$301,$A18,'Coded Responses'!$K$2:$K$301,"*"&E$12&"*") -> 13 | F18: =COUNTIFS('Coded Responses'!$B$2:$B$301,$A18,'Coded Responses'!$K$2:$K$301,"*"&F$12&"*") -> 10 | G18: =COUNTIFS('Coded Responses'!$B$2:$B$301,$A18,'Coded Responses'!$K$2:$K$301,"*"&G$12&"*") -> 9 | H18: =SUM(B18:G18) -> 78
A19: Total | B19: =SUM(B13:B18) -> 83 | C19: =SUM(C13:C18) -> 80 | D19: =SUM(D13:D18) -> 78 | E19: =SUM(E13:E18) -> 72 | F19: =SUM(F13:F18) -> 72 | G19: =SUM(G13:G18) -> 66 | H19: =SUM(H13:H18) -> 451

Sheet Likert Summary
A1: Question | B1: Average score | C1: % low (1-2) | D1: % high (4-5)
A2: q1 | B2: =AVERAGE('Coded Responses'!$D$2:$D$301) -> 3.28 | C2: =COUNTIF('Coded Responses'!$D$2:$D$301,"<=2")/COUNT('Coded Responses'!$D$2:$D$301) -> 0.23333333 | D2: =COUNTIF('Coded Responses'!$D$2:$D$301,">=4")/COUNT('Coded Responses'!$D$2:$D$301) -> 0.44333333
A3: q2 | B3: =AVERAGE('Coded Responses'!$E$2:$E$301) -> 3.25 | C3: =COUNTIF('Coded Responses'!$E$2:$E$301,"<=2")/COUNT('Coded Responses'!$E$2:$E$301) -> 0.22666667 | D3: =COUNTIF('Coded Responses'!$E$2:$E$301,">=4")/COUNT('Coded Responses'!$E$2:$E$301) -> 0.39
A4: q3 | B4: =AVERAGE('Coded Responses'!$F$2:$F$301) -> 3.3066667 | C4: =COUNTIF('Coded Responses'!$F$2:$F$301,"<=2")/COUNT('Coded Responses'!$F$2:$F$301) -> 0.22 | D4: =COUNTIF('Coded Responses'!$F$2:$F$301,">=4")/COUNT('Coded Responses'!$F$2:$F$301) -> 0.43333333
A5: q4 | B5: =AVERAGE('Coded Responses'!$G$2:$G$301) -> 3.3066667 | C5: =COUNTIF('Coded Responses'!$G$2:$G$301,"<=2")/COUNT('Coded Responses'!$G$2:$G$301) -> 0.2 | D5: =COUNTIF('Coded Responses'!$G$2:$G$301,">=4")/COUNT('Coded Responses'!$G$2:$G$301) -> 0.43
A6: q5 | B6: =AVERAGE('Coded Responses'!$H$2:$H$301) -> 3.4233333 | C6: =COUNTIF('Coded Responses'!$H$2:$H$301,"<=2")/COUNT('Coded Responses'!$H$2:$H$301) -> 0.18333333 | D6: =COUNTIF('Coded Responses'!$H$2:$H$301,">=4")/COUNT('Coded Responses'!$H$2:$H$301) -> 0.49
A8: Average score by department
A9: Department | B9: q1 | C9: q2 | D9: q3 | E9: q4 | F9: q5
A10: Customer Support | B10: =AVERAGEIFS('Coded Responses'!$D$2:$D$301,'Coded Responses'!$B$2:$B$301,$A10) -> 3.3829787 | C10: =AVERAGEIFS('Coded Responses'!$E$2:$E$301,'Coded Responses'!$B$2:$B$301,$A10) -> 3.0638298 | D10: =AVERAGEIFS('Coded Responses'!$F$2:$F$301,'Coded Responses'!$B$2:$B$301,$A10) -> 3.0851064 | E10: =AVERAGEIFS('Coded Responses'!$G$2:$G$301,'Coded Responses'!$B$2:$B$301,$A10) -> 3.2765957 | F10: =AVERAGEIFS('Coded Responses'!$H$2:$H$301,'Coded Responses'!$B$2:$B$301,$A10) -> 3.3404255
A11: Finance | B11: =AVERAGEIFS('Coded Responses'!$D$2:$D$301,'Coded Responses'!$B$2:$B$301,$A11) -> 3.2407407 | C11: =AVERAGEIFS('Coded Responses'!$E$2:$E$301,'Coded Responses'!$B$2:$B$301,$A11) -> 3.2037037 | D11: =AVERAGEIFS('Coded Responses'!$F$2:$F$301,'Coded Responses'!$B$2:$B$301,$A11) -> 3.3333333 | E11: =AVERAGEIFS('Coded Responses'!$G$2:$G$301,'Coded Responses'!$B$2:$B$301,$A11) -> 3.2777778 | F11: =AVERAGEIFS('Coded Responses'!$H$2:$H$301,'Coded Responses'!$B$2:$B$301,$A11) -> 3.6296296
A12: HR | B12: =AVERAGEIFS('Coded Responses'!$D$2:$D$301,'Coded Responses'!$B$2:$B$301,$A12) -> 3.4468085 | C12: =AVERAGEIFS('Coded Responses'!$E$2:$E$301,'Coded Responses'!$B$2:$B$301,$A12) -> 3.2765957 | D12: =AVERAGEIFS('Coded Responses'!$F$2:$F$301,'Coded Responses'!$B$2:$B$301,$A12) -> 3.2340426 | E12: =AVERAGEIFS('Coded Responses'!$G$2:$G$301,'Coded Responses'!$B$2:$B$301,$A12) -> 3.1702128 | F12: =AVERAGEIFS('Coded Responses'!$H$2:$H$301,'Coded Responses'!$B$2:$B$301,$A12) -> 3.3617021
A13: Operations | B13: =AVERAGEIFS('Coded Responses'!$D$2:$D$301,'Coded Responses'!$B$2:$B$301,$A13) -> 2.9791667 | C13: =AVERAGEIFS('Coded Responses'!$E$2:$E$301,'Coded Responses'!$B$2:$B$301,$A13) -> 3.25 | D13: =AVERAGEIFS('Coded Responses'!$F$2:$F$301,'Coded Responses'!$B$2:$B$301,$A13) -> 3.2291667 | E13: =AVERAGEIFS('Coded Responses'!$G$2:$G$301,'Coded Responses'!$B$2:$B$301,$A13) -> 3.1458333 | F13: =AVERAGEIFS('Coded Responses'!$H$2:$H$301,'Coded Responses'!$B$2:$B$301,$A13) -> 3.2083333
A14: Sales | B14: =AVERAGEIFS('Coded Responses'!$D$2:$D$301,'Coded Responses'!$B$2:$B$301,$A14) -> 3.3207547 | C14: =AVERAGEIFS('Coded Responses'!$E$2:$E$301,'Coded Responses'!$B$2:$B$301,$A14) -> 3.3584906 | D14: =AVERAGEIFS('Coded Responses'!$F$2:$F$301,'Coded Responses'!$B$2:$B$301,$A14) -> 3.3396226 | E14: =AVERAGEIFS('Coded Responses'!$G$2:$G$301,'Coded Responses'!$B$2:$B$301,$A14) -> 3.3773585 | F14: =AVERAGEIFS('Coded Responses'!$H$2:$H$301,'Coded Responses'!$B$2:$B$301,$A14) -> 3.509434
A15: Technology | B15: =AVERAGEIFS('Coded Responses'!$D$2:$D$301,'Coded Responses'!$B$2:$B$301,$A15) -> 3.3137255 | C15: =AVERAGEIFS('Coded Responses'!$E$2:$E$301,'Coded Responses'!$B$2:$B$301,$A15) -> 3.3333333 | D15: =AVERAGEIFS('Coded Responses'!$F$2:$F$301,'Coded Responses'!$B$2:$B$301,$A15) -> 3.5882353 | E15: =AVERAGEIFS('Coded Responses'!$G$2:$G$301,'Coded Responses'!$B$2:$B$301,$A15) -> 3.5686275 | F15: =AVERAGEIFS('Coded Responses'!$H$2:$H$301,'Coded Responses'!$B$2:$B$301,$A15) -> 3.4509804
A16: All departments | B16: =AVERAGE('Coded Responses'!$D$2:$D$301) -> 3.28 | C16: =AVERAGE('Coded Responses'!$E$2:$E$301) -> 3.25 | D16: =AVERAGE('Coded Responses'!$F$2:$F$301) -> 3.3066667 | E16: =AVERAGE('Coded Responses'!$G$2:$G$301) -> 3.3066667 | F16: =AVERAGE('Coded Responses'!$H$2:$H$301) -> 3.4233333

Sheet Theme vs Likert
A1: Theme | B1: Linked question | C1: Negative comments | D1: % Negative with low linked score | E1: Avg linked score - Negative | F1: Avg linked score - Everyone else | G1: eNPS - Negative | H1: eNPS - Everyone else
A2: Manager support | B2: q2_manager_support_1to5 | C2: =COUNTIF('Coded Responses'!$M$2:$M$301,"Manager support Negative") -> 45 | D2: =COUNTIFS('Coded Responses'!$M$2:$M$301,"Manager support Negative",'Coded Responses'!$E$2:$E$301,"<=2")/COUNTIF('Coded Responses'!$M$2:$M$301,"Manager support Negative") -> 0.31111111 | E2: =AVERAGEIFS('Coded Responses'!$E$2:$E$301,'Coded Responses'!$M$2:$M$301,"Manager support Negative") -> 2.8888889 | F2: =AVERAGEIFS('Coded Responses'!$E$2:$E$301,'Coded Responses'!$M$2:$M$301,"Everyone else") -> 3.3137255 | G2: =100*(COUNTIFS('Coded Responses'!$M$2:$M$301,"Manager support Negative",'Coded Responses'!$I$2:$I$301,">=9")/COUNTIF('Coded Responses'!$M$2:$M$301,"Manager support Negative")-COUNTIFS('Coded Responses'!$M$2:$M$301,"Manager support Negative",'Coded Responses'!$I$2:$I$301,"<=6")/COUNTIF('Coded Responses'!$M$2:$M$301,"Manager support Negative")) -> -75.555556 | H2: =100*(COUNTIFS('Coded Responses'!$M$2:$M$301,"Everyone else",'Coded Responses'!$I$2:$I$301,">=9")/COUNTIF('Coded Responses'!$M$2:$M$301,"Everyone else")-COUNTIFS('Coded Responses'!$M$2:$M$301,"Everyone else",'Coded Responses'!$I$2:$I$301,"<=6")/COUNTIF('Coded Responses'!$M$2:$M$301,"Everyone else")) -> -36.078431
A3: Pay and benefits | B3: q3_fair_pay_1to5 | C3: =COUNTIF('Coded Responses'!$Q$2:$Q$301,"Pay and benefits Negative") -> 38 | D3: =COUNTIFS('Coded Responses'!$Q$2:$Q$301,"Pay and benefits Negative",'Coded Responses'!$F$2:$F$301,"<=2")/COUNTIF('Coded Responses'!$Q$2:$Q$301,"Pay and benefits Negative") -> 0.44736842 | E3: =AVERAGEIFS('Coded Responses'!$F$2:$F$301,'Coded Responses'!$Q$2:$Q$301,"Pay and benefits Negative") -> 2.6842105 | F3: =AVERAGEIFS('Coded Responses'!$F$2:$F$301,'Coded Responses'!$Q$2:$Q$301,"Everyone else") -> 3.3969466 | G3: =100*(COUNTIFS('Coded Responses'!$Q$2:$Q$301,"Pay and benefits Negative",'Coded Responses'!$I$2:$I$301,">=9")/COUNTIF('Coded Responses'!$Q$2:$Q$301,"Pay and benefits Negative")-COUNTIFS('Coded Responses'!$Q$2:$Q$301,"Pay and benefits Negative",'Coded Responses'!$I$2:$I$301,"<=6")/COUNTIF('Coded Responses'!$Q$2:$Q$301,"Pay and benefits Negative")) -> -78.947368 | H3: =100*(COUNTIFS('Coded Responses'!$Q$2:$Q$301,"Everyone else",'Coded Responses'!$I$2:$I$301,">=9")/COUNTIF('Coded Responses'!$Q$2:$Q$301,"Everyone else")-COUNTIFS('Coded Responses'!$Q$2:$Q$301,"Everyone else",'Coded Responses'!$I$2:$I$301,"<=6")/COUNTIF('Coded Responses'!$Q$2:$Q$301,"Everyone else")) -> -36.641221
A4: Career growth | B4: q4_growth_1to5 | C4: =COUNTIF('Coded Responses'!$R$2:$R$301,"Career growth Negative") -> 35 | D4: =COUNTIFS('Coded Responses'!$R$2:$R$301,"Career growth Negative",'Coded Responses'!$G$2:$G$301,"<=2")/COUNTIF('Coded Responses'!$R$2:$R$301,"Career growth Negative") -> 0.4 | E4: =AVERAGEIFS('Coded Responses'!$G$2:$G$301,'Coded Responses'!$R$2:$R$301,"Career growth Negative") -> 2.7714286 | F4: =AVERAGEIFS('Coded Responses'!$G$2:$G$301,'Coded Responses'!$R$2:$R$301,"Everyone else") -> 3.3773585 | G4: =100*(COUNTIFS('Coded Responses'!$R$2:$R$301,"Career growth Negative",'Coded Responses'!$I$2:$I$301,">=9")/COUNTIF('Coded Responses'!$R$2:$R$301,"Career growth Negative")-COUNTIFS('Coded Responses'!$R$2:$R$301,"Career growth Negative",'Coded Responses'!$I$2:$I$301,"<=6")/COUNTIF('Coded Responses'!$R$2:$R$301,"Career growth Negative")) -> -60 | H4: =100*(COUNTIFS('Coded Responses'!$R$2:$R$301,"Everyone else",'Coded Responses'!$I$2:$I$301,">=9")/COUNTIF('Coded Responses'!$R$2:$R$301,"Everyone else")-COUNTIFS('Coded Responses'!$R$2:$R$301,"Everyone else",'Coded Responses'!$I$2:$I$301,"<=6")/COUNTIF('Coded Responses'!$R$2:$R$301,"Everyone else")) -> -39.622642
A5: Flexibility | B5: q5_worklife_balance_1to5 | C5: =COUNTIF('Coded Responses'!$N$2:$N$301,"Flexibility Negative") -> 49 | D5: =COUNTIFS('Coded Responses'!$N$2:$N$301,"Flexibility Negative",'Coded Responses'!$H$2:$H$301,"<=2")/COUNTIF('Coded Responses'!$N$2:$N$301,"Flexibility Negative") -> 0.30612245 | E5: =AVERAGEIFS('Coded Responses'!$H$2:$H$301,'Coded Responses'!$N$2:$N$301,"Flexibility Negative") -> 2.9387755 | F5: =AVERAGEIFS('Coded Responses'!$H$2:$H$301,'Coded Responses'!$N$2:$N$301,"Everyone else") -> 3.5179283 | G5: =100*(COUNTIFS('Coded Responses'!$N$2:$N$301,"Flexibility Negative",'Coded Responses'!$I$2:$I$301,">=9")/COUNTIF('Coded Responses'!$N$2:$N$301,"Flexibility Negative")-COUNTIFS('Coded Responses'!$N$2:$N$301,"Flexibility Negative",'Coded Responses'!$I$2:$I$301,"<=6")/COUNTIF('Coded Responses'!$N$2:$N$301,"Flexibility Negative")) -> -75.510204 | H5: =100*(COUNTIFS('Coded Responses'!$N$2:$N$301,"Everyone else",'Coded Responses'!$I$2:$I$301,">=9")/COUNTIF('Coded Responses'!$N$2:$N$301,"Everyone else")-COUNTIFS('Coded Responses'!$N$2:$N$301,"Everyone else",'Coded Responses'!$I$2:$I$301,"<=6")/COUNTIF('Coded Responses'!$N$2:$N$301,"Everyone else")) -> -35.458167
A6: Workload | B6: q5_worklife_balance_1to5 | C6: =COUNTIF('Coded Responses'!$O$2:$O$301,"Workload Negative") -> 40 | D6: =COUNTIFS('Coded Responses'!$O$2:$O$301,"Workload Negative",'Coded Responses'!$H$2:$H$301,"<=2")/COUNTIF('Coded Responses'!$O$2:$O$301,"Workload Negative") -> 0.2 | E6: =AVERAGEIFS('Coded Responses'!$H$2:$H$301,'Coded Responses'!$O$2:$O$301,"Workload Negative") -> 3.15 | F6: =AVERAGEIFS('Coded Responses'!$H$2:$H$301,'Coded Responses'!$O$2:$O$301,"Everyone else") -> 3.4653846 | G6: =100*(COUNTIFS('Coded Responses'!$O$2:$O$301,"Workload Negative",'Coded Responses'!$I$2:$I$301,">=9")/COUNTIF('Coded Responses'!$O$2:$O$301,"Workload Negative")-COUNTIFS('Coded Responses'!$O$2:$O$301,"Workload Negative",'Coded Responses'!$I$2:$I$301,"<=6")/COUNTIF('Coded Responses'!$O$2:$O$301,"Workload Negative")) -> -87.5 | H6: =100*(COUNTIFS('Coded Responses'!$O$2:$O$301,"Everyone else",'Coded Responses'!$I$2:$I$301,">=9")/COUNTIF('Coded Responses'!$O$2:$O$301,"Everyone else")-COUNTIFS('Coded Responses'!$O$2:$O$301,"Everyone else",'Coded Responses'!$I$2:$I$301,"<=6")/COUNTIF('Coded Responses'!$O$2:$O$301,"Everyone else")) -> -35
A7: Tools and systems | B7: q1_clear_goals_1to5 | C7: =COUNTIF('Coded Responses'!$P$2:$P$301,"Tools and systems Negative") -> 41 | D7: =COUNTIFS('Coded Responses'!$P$2:$P$301,"Tools and systems Negative",'Coded Responses'!$D$2:$D$301,"<=2")/COUNTIF('Coded Responses'!$P$2:$P$301,"Tools and systems Negative") -> 0.36585366 | E7: =AVERAGEIFS('Coded Responses'!$D$2:$D$301,'Coded Responses'!$P$2:$P$301,"Tools and systems Negative") -> 2.6097561 | F7: =AVERAGEIFS('Coded Responses'!$D$2:$D$301,'Coded Responses'!$P$2:$P$301,"Everyone else") -> 3.3861004 | G7: =100*(COUNTIFS('Coded Responses'!$P$2:$P$301,"Tools and systems Negative",'Coded Responses'!$I$2:$I$301,">=9")/COUNTIF('Coded Responses'!$P$2:$P$301,"Tools and systems Negative")-COUNTIFS('Coded Responses'!$P$2:$P$301,"Tools and systems Negative",'Coded Responses'!$I$2:$I$301,"<=6")/COUNTIF('Coded Responses'!$P$2:$P$301,"Tools and systems Negative")) -> -78.04878 | H7: =100*(COUNTIFS('Coded Responses'!$P$2:$P$301,"Everyone else",'Coded Responses'!$I$2:$I$301,">=9")/COUNTIF('Coded Responses'!$P$2:$P$301,"Everyone else")-COUNTIFS('Coded Responses'!$P$2:$P$301,"Everyone else",'Coded Responses'!$I$2:$I$301,"<=6")/COUNTIF('Coded Responses'!$P$2:$P$301,"Everyone else")) -> -36.293436
A9: Workload (Negative comments) - check
A10: Measure | B10: Value
A11: Negative Workload comments | B11: =COUNTIF('Coded Responses'!$O$2:$O$301,"Workload Negative") -> 40
A12: Low q5 count (1-2) | B12: =COUNTIFS('Coded Responses'!$O$2:$O$301,"Workload Negative",'Coded Responses'!$H$2:$H$301,"<=2") -> 8
A13: % low q5 | B13: =COUNTIFS('Coded Responses'!$O$2:$O$301,"Workload Negative",'Coded Responses'!$H$2:$H$301,"<=2")/COUNTIF('Coded Responses'!$O$2:$O$301,"Workload Negative") -> 0.2
A14: Average q5 | B14: =AVERAGEIFS('Coded Responses'!$H$2:$H$301,'Coded Responses'!$O$2:$O$301,"Workload Negative") -> 3.15
A15: Workload Negative eNPS | B15: =100*(COUNTIFS('Coded Responses'!$O$2:$O$301,"Workload Negative",'Coded Responses'!$I$2:$I$301,">=9")/COUNTIF('Coded Responses'!$O$2:$O$301,"Workload Negative")-COUNTIFS('Coded Responses'!$O$2:$O$301,"Workload Negative",'Coded Responses'!$I$2:$I$301,"<=6")/COUNTIF('Coded Responses'!$O$2:$O$301,"Workload Negative")) -> -87.5

Sheet Accuracy Check (50 rows)
A1: response_id | B1: comment | C1: my_themes | D1: gold_themes | E1: my_tone | F1: gold_tone | G1: match | I1: Measure | J1: Value
A2: ='Coded Responses'!A2 -> R0001 | B2: ='Coded Responses'!J2 -> My manager gives regular, useful feedback. | C2: ='Coded Responses'!K2 -> Manager support | D2: Manager support | E2: ='Coded Responses'!L2 -> Positive | F2: Positive | G2: =IF(AND(C2=D2,E2=F2),"Yes","No") -> Yes | I2: Rows checked | J2: =COUNTA(D2:D51) -> 50
A3: ='Coded Responses'!A3 -> R0002 | B3: ='Coded Responses'!J3 -> Flexible hours are very helpful. | C3: ='Coded Responses'!K3 -> Flexibility | D3: Flexibility | E3: ='Coded Responses'!L3 -> Positive | F3: Positive | G3: =IF(AND(C3=D3,E3=F3),"Yes","No") -> Yes | I3: Number correct | J3: =COUNTIF(G2:G51,"Yes") -> 50
A4: ='Coded Responses'!A4 -> R0003 | B4: ='Coded Responses'!J4 -> My manager gives regular, useful feedback. Hybrid work helps me balance family. | C4: ='Coded Responses'!K4 -> Manager support; Flexibility | D4: Manager support; Flexibility | E4: ='Coded Responses'!L4 -> Positive | F4: Positive | G4: =IF(AND(C4=D4,E4=F4),"Yes","No") -> Yes | I4: Number wrong | J4: =COUNTIF(G2:G51,"No") -> 0
A5: ='Coded Responses'!A5 -> R0004 | B5: ='Coded Responses'!J5 -> We still use too many manual Excel reports. My manager rarely has time for one-on-ones. | C5: ='Coded Responses'!K5 -> Tools and systems; Manager support | D5: Tools and systems; Manager support | E5: ='Coded Responses'!L5 -> Negative | F5: Negative | G5: =IF(AND(C5=D5,E5=F5),"Yes","No") -> Yes | I5: Accuracy % | J5: =IF(J2=0,"",J3/J2) -> 1
A6: ='Coded Responses'!A6 -> R0005 | B6: ='Coded Responses'!J6 -> I was promoted on time and learnt a lot. | C6: ='Coded Responses'!K6 -> Career growth | D6: Career growth | E6: ='Coded Responses'!L6 -> Positive | F6: Positive | G6: =IF(AND(C6=D6,E6=F6),"Yes","No") -> Yes
A7: ='Coded Responses'!A7 -> R0006 | B7: ='Coded Responses'!J7 -> Staff shortage means we do two people's work. | C7: ='Coded Responses'!K7 -> Workload | D7: Workload | E7: ='Coded Responses'!L7 -> Negative | F7: Negative | G7: =IF(AND(C7=D7,E7=F7),"Yes","No") -> Yes | I7: Rows checked: R0001 to R0050 (the first 50 coded responses). A row is "Yes" only when both themes and tone match the gold labels.
A8: ='Coded Responses'!A8 -> R0007 | B8: ='Coded Responses'!J8 -> Internal jobs go to outsiders first. | C8: ='Coded Responses'!K8 -> Career growth | D8: Career growth | E8: ='Coded Responses'!L8 -> Negative | F8: Negative | G8: =IF(AND(C8=D8,E8=F8),"Yes","No") -> Yes | I8: Gold labels were used only for this check and were never given to the AI tool.
A9: ='Coded Responses'!A9 -> R0008 | B9: ='Coded Responses'!J9 -> Increments did not match inflation this year. Feedback only comes during appraisal. | C9: ='Coded Responses'!K9 -> Pay and benefits; Manager support | D9: Pay and benefits; Manager support | E9: ='Coded Responses'!L9 -> Negative | F9: Negative | G9: =IF(AND(C9=D9,E9=F9),"Yes","No") -> Yes | I9: Limit: this data repeats a small set of short sentences, so a very high score is expected. It does not prove the method will work as well on real, messy comments.
A10: ='Coded Responses'!A10 -> R0009 | B10: ='Coded Responses'!J10 -> My manager rarely has time for one-on-ones. | C10: ='Coded Responses'!K10 -> Manager support | D10: Manager support | E10: ='Coded Responses'!L10 -> Negative | F10: Negative | G10: =IF(AND(C10=D10,E10=F10),"Yes","No") -> Yes
A11: ='Coded Responses'!A11 -> R0010 | B11: ='Coded Responses'!J11 -> No clear promotion criteria. | C11: ='Coded Responses'!K11 -> Career growth | D11: Career growth | E11: ='Coded Responses'!L11 -> Negative | F11: Negative | G11: =IF(AND(C11=D11,E11=F11),"Yes","No") -> Yes
A12: ='Coded Responses'!A12 -> R0011 | B12: ='Coded Responses'!J12 -> Leave approvals are very slow. | C12: ='Coded Responses'!K12 -> Flexibility | D12: Flexibility | E12: ='Coded Responses'!L12 -> Negative | F12: Negative | G12: =IF(AND(C12=D12,E12=F12),"Yes","No") -> Yes
A13: ='Coded Responses'!A13 -> R0012 | B13: ='Coded Responses'!J13 -> Internal jobs go to outsiders first. | C13: ='Coded Responses'!K13 -> Career growth | D13: Career growth | E13: ='Coded Responses'!L13 -> Negative | F13: Negative | G13: =IF(AND(C13=D13,E13=F13),"Yes","No") -> Yes
A14: ='Coded Responses'!A14 -> R0013 | B14: ='Coded Responses'!J14 -> Increments did not match inflation this year. Internal jobs go to outsiders first. | C14: ='Coded Responses'!K14 -> Pay and benefits; Career growth | D14: Pay and benefits; Career growth | E14: ='Coded Responses'!L14 -> Negative | F14: Negative | G14: =IF(AND(C14=D14,E14=F14),"Yes","No") -> Yes
A15: ='Coded Responses'!A15 -> R0014 | B15: ='Coded Responses'!J15 -> Health insurance for parents is a big plus. I was promoted on time and learnt a lot. | C15: ='Coded Responses'!K15 -> Pay and benefits; Career growth | D15: Pay and benefits; Career growth | E15: ='Coded Responses'!L15 -> Positive | F15: Positive | G15: =IF(AND(C15=D15,E15=F15),"Yes","No") -> Yes
A16: ='Coded Responses'!A16 -> R0015 | B16: ='Coded Responses'!J16 -> Staff shortage means we do two people's work. We still use too many manual Excel reports. | C16: ='Coded Responses'!K16 -> Workload; Tools and systems | D16: Workload; Tools and systems | E16: ='Coded Responses'!L16 -> Negative | F16: Negative | G16: =IF(AND(C16=D16,E16=F16),"Yes","No") -> Yes
A17: ='Coded Responses'!A17 -> R0016 | B17: ='Coded Responses'!J17 -> Increments did not match inflation this year. | C17: ='Coded Responses'!K17 -> Pay and benefits | D17: Pay and benefits | E17: ='Coded Responses'!L17 -> Negative | F17: Negative | G17: =IF(AND(C17=D17,E17=F17),"Yes","No") -> Yes
A18: ='Coded Responses'!A18 -> R0017 | B18: ='Coded Responses'!J18 -> Leave approvals are very slow. | C18: ='Coded Responses'!K18 -> Flexibility | D18: Flexibility | E18: ='Coded Responses'!L18 -> Negative | F18: Negative | G18: =IF(AND(C18=D18,E18=F18),"Yes","No") -> Yes
A19: ='Coded Responses'!A19 -> R0018 | B19: ='Coded Responses'!J19 -> Leave approvals are very slow. Staff shortage means we do two people's work. | C19: ='Coded Responses'!K19 -> Flexibility; Workload | D19: Flexibility; Workload | E19: ='Coded Responses'!L19 -> Negative | F19: Negative | G19: =IF(AND(C19=D19,E19=F19),"Yes","No") -> Yes
A20: ='Coded Responses'!A20 -> R0019 | B20: ='Coded Responses'!J20 -> My manager rarely has time for one-on-ones. Increments did not match inflation this year. | C20: ='Coded Responses'!K20 -> Manager support; Pay and benefits | D20: Manager support; Pay and benefits | E20: ='Coded Responses'!L20 -> Negative | F20: Negative | G20: =IF(AND(C20=D20,E20=F20),"Yes","No") -> Yes
A21: ='Coded Responses'!A21 -> R0020 | B21: ='Coded Responses'!J21 -> Systems are slow and crash often. | C21: ='Coded Responses'!K21 -> Tools and systems | D21: Tools and systems | E21: ='Coded Responses'!L21 -> Negative | F21: Negative | G21: =IF(AND(C21=D21,E21=F21),"Yes","No") -> Yes
... A51: ='Coded Responses'!A51 -> R0050 | B51: ='Coded Responses'!J51 -> My manager rarely has time for one-on-ones. Systems are slow and crash often. | C51: ='Coded Responses'!K51 -> Manager support; Tools and systems | D51: Manager support; Tools and systems | E51: ='Coded Responses'!L51 -> Negative | F51: Negative | G51: =IF(AND(C51=D51,E51=F51),"Yes","No") -> Yes
